twat_audio/__version__.py
twat_audio/twat_audio.py
twat_audio-2.7.5.dist-info/METADATA
twat_audio-2.7.5.dist-info/WHEEL
twat_audio-2.7.5.dist-info/licenses/LICENSE
twat_audio-2.7.5.dist-info/RECORD
